basic/5_Seqimtial_Circuit_Design/5_FIFO_Buffer/fifo.v
// FIFO

module fifo (clk, clrn, read, write, data_in, data_out, ready, overflow);

	input clk, clrn;
	input read, write;					// read and wirte, active high
	input [7:0] data_in;
	output [7:0] data_out;
	output ready;						// fifo has data
	output reg overflow;				// fifo overflow flag

	reg [7:0] fifo_buffer [7:0];		// fifo buffer of depth 8
	reg [2:0] write_pointer;
	reg [2:0] read_pointer;
	
	always @ (posedge clk or negedge clrn) begin
		if (!clrn)	begin
			write_pointer <= 0;
			read_pointer <= 0;
			overflow <= 0;
		end	//if_!clrn
		else begin
			if (write) begin
				if((write_pointer + 3'b1) != read_pointer) begin
					fifo_buffer[write_pointer] <= data_in;
					write_pointer <= write_pointer + 3'b1;
				end //if
				else begin
					overflow <= 1;
				end // else
			end //if_write
			
			if (read && ready) begin
				read_pointer <= read_pointer + 3'b1;
				overflow <= 0;
			end //if_read
			
		end //else
	end //always
	
	assign ready = (write_pointer != read_pointer);
	assign data_out = fifo_buffer[read_pointer];
	
endmodule

Basic/5_Seqimtial_Circuit_Design/5_FIFO_Buffer/fifo_tb.v
`timescale 1ns/1ns

module fifo_tb;
	reg clk, clrn;
	reg read, write;
	reg [7:0] data_in;
	wire [7:0] data_out;
	wire ready;
	wire overflow;

	fifo fifo (clk, clrn, read, write, data_in, data_out, ready, overflow);

	initial begin
		#0 clk 	= 0;
		   clrn = 0;
		   read = 0;
		   write = 0;

		#2 clrn = 1;
	       write = 1;
		   data_in = 8'he0;
		#2 data_in = 8'he1;
		#2 data_in = 8'he2;
		#2 data_in = 8'he3;
		#2 data_in = 8'he4;
		#2 data_in = 8'he5;
			read = 1;

		#2 data_in = 8'he6;
		#2 data_in = 8'he7;
		#2 data_in = 8'he8;
			read = 0;

		#2 data_in = 8'he9;
		#2 data_in = 8'hea;
		#2 data_in = 8'heb;
		#2 data_in = 8'hec;
		#2 data_in = 8'hed;
		#2 data_in = 8'hee;
		#2 data_in = 8'hef;
		#2 data_in = 8'hf0;
			read = 1;
		#2 data_in = 8'hf1;
		#2 data_in = 8'hf2;
			read = 0;
		#2 data_in = 8'hf3;
			read = 1;
		#2 data_in = 8'hf4;
			write = 0;
		#5 $finish;
	end

	always #1 clk = !clk;

	initial begin
		$dumpfile("fifo.vcd");
		$dumpvars;
	end

endmodule

basic/5_Seqimtial_Circuit_Design/5_FIFO_Buffer/fifo.vcd
$date
	Thu Feb  1 23:07:56 2018
$end
$version
	Icarus Verilog
$end
$timescale
	1ns
$end
$scope module fifo_tb $end
$var wire 1 ! ready $end
$var wire 1 " overflow $end
$var wire 8 # data_out [7:0] $end
$var reg 1 $ clk $end
$var reg 1 % clrn $end
$var reg 8 & data_in [7:0] $end
$var reg 1 ' read $end
$var reg 1 ( write $end
$scope module fifo $end
$var wire 1 $ clk $end
$var wire 1 % clrn $end
$var wire 8 ) data_in [7:0] $end
$var wire 8 * data_out [7:0] $end
$var wire 1 ' read $end
$var wire 1 ( write $end
$var wire 1 ! ready $end
$var reg 1 " overflow $end
$var reg 3 + read_pointer [2:0] $end
$var reg 3 , write_pointer [2:0] $end
$upscope $end
$upscope $end
$enddefinitions $end
#0
$dumpvars
b0 ,
b0 +
bx *
bx )
0(
0'
bx &
0%
0$
bx #
0"
0!
$end
#1
1$
#2
0$
b11100000 &
b11100000 )
1(
1%
#3
1!
b1 ,
b11100000 #
b11100000 *
1$
#4
0$
b11100001 &
b11100001 )
#5
b10 ,
1$
#6
0$
b11100010 &
b11100010 )
#7
b11 ,
1$
#8
0$
b11100011 &
b11100011 )
#9
b100 ,
1$
#10
0$
b11100100 &
b11100100 )
#11
b101 ,
1$
#12
0$
1'
b11100101 &
b11100101 )
#13
b11100001 #
b11100001 *
b1 +
b110 ,
1$
#14
0$
b11100110 &
b11100110 )
#15
b11100010 #
b11100010 *
b10 +
b111 ,
1$
#16
0$
b11100111 &
b11100111 )
#17
b11100011 #
b11100011 *
b11 +
b0 ,
1$
#18
0$
0'
b11101000 &
b11101000 )
#19
b1 ,
1$
#20
0$
b11101001 &
b11101001 )
#21
b10 ,
1$
#22
0$
b11101010 &
b11101010 )
#23
1"
1$
#24
0$
b11101011 &
b11101011 )
#25
1$
#26
0$
b11101100 &
b11101100 )
#27
1$
#28
0$
b11101101 &
b11101101 )
#29
1$
#30
0$
b11101110 &
b11101110 )
#31
1$
#32
0$
b11101111 &
b11101111 )
#33
1$
#34
0$
1'
b11110000 &
b11110000 )
#35
0"
b11100100 #
b11100100 *
b100 +
1$
#36
0$
b11110001 &
b11110001 )
#37
b11100101 #
b11100101 *
b101 +
b11 ,
1$
#38
0$
0'
b11110010 &
b11110010 )
#39
b100 ,
1$
#40
0$
1'
b11110011 &
b11110011 )
#41
b11100110 #
b11100110 *
b110 +
0"
1$
#42
0$
0(
b11110100 &
b11110100 )
#43
b11100111 #
b11100111 *
b111 +
1$
#44
0$
#45
b11101000 #
b11101000 *
b0 +
1$
#46
0$
#47
b11101001 #
b11101001 *
b1 +
1$
