Basic/5_Seqimtial_Circuit_Design/1_D_Latch_and_D_Flip_Flop/D_Latch/rs_latch.v
// a RS(reset-set) latch
module rs_latch (s, r, q, qn);
	
	input r, s;
	output q, qn;
	
	nand nand1 (q, s, qn);
	nand nand2 (qn, r, q);
	
endmodule

Basic/5_Seqimtial_Circuit_Design/1_D_Latch_and_D_Flip_Flop/D_Flip_Flop/d_latch.v
// a D latch, which can store one bit information
module d_latch (d, c, q, qn);

	input d, c;
	output q, qn;
	
	wire r, s;
	
	nand nand1 (s, d, c);
	nand nand2 (r, ~d, c);
	
	rs_latch rs (s, r, q, qn);	
endmodule

Basic/5_Seqimtial_Circuit_Design/1_D_Latch_and_D_Flip_Flop/D_Latch/d_latch_tb.v
`timescale 1ns/1ns

module d_latch_tb;
	
	reg c, d;
	wire q, qn;

	d_latch d_latch (c, d, q, qn);

	initial begin
		#0  c = 0; d = 0;
		#28 $finish;
	end

	initial begin
		$dumpfile("d_latch.vcd");
		$dumpvars;
	end 

	always #4 c = !c;
	always #3 d = !d;

endmodule

basic/5_Seqimtial_Circuit_Design/1_D_Latch_and_D_Flip_Flop/D_Latch/d_latch.vcd
$date
	Wed Jan 31 20:18:40 2018
$end
$version
	Icarus Verilog
$end
$timescale
	1ns
$end
$scope module d_latch_tb $end
$var wire 1 ! qn $end
$var wire 1 " q $end
$var reg 1 # c $end
$var reg 1 $ d $end
$scope module d_latch $end
$var wire 1 $ c $end
$var wire 1 # d $end
$var wire 1 % r $end
$var wire 1 & s $end
$var wire 1 ! qn $end
$var wire 1 " q $end
$scope module rs $end
$var wire 1 " q $end
$var wire 1 ! qn $end
$var wire 1 % r $end
$var wire 1 & s $end
$upscope $end
$upscope $end
$upscope $end
$enddefinitions $end
#0
$dumpvars
1&
1%
0$
0#
x"
x!
$end
#3
0"
1!
0%
1$
#4
0!
1"
1%
0&
1#
#6
1&
0$
#8
0#
#9
0"
1!
0%
1$
#12
1%
0$
1#
#15
0!
1"
0&
1$
#16
0"
1!
0%
1&
0#
#18
1%
0$
#20
1#
#21
0!
1"
0&
1$
#24
1&
0$
0#
#27
0"
1!
0%
1$
#28
0!
1"
1%
0&
1#
