Basic/5_Seqimtial_Circuit_Design/1_D_Latch_and_D_Flip_Flop/D_Latch/rs_latch.v
// a RS(reset-set) latch
module rs_latch (s, r, q, qn);
	
	input r, s;
	output q, qn;
	
	nand nand1 (q, s, qn);
	nand nand2 (qn, r, q);
	
endmodule

Basic/5_Seqimtial_Circuit_Design/1_D_Latch_and_D_Flip_Flop/D_Flip_Flop/d_latch.v
// a D latch, which can store one bit information
module d_latch (d, c, q, qn);

	input d, c;
	output q, qn;
	
	wire r, s;
	
	nand nand1 (s, d, c);
	nand nand2 (r, ~d, c);
	
	rs_latch rs (s, r, q, qn);	
endmodule

basic/5_Seqimtial_Circuit_Design/1_D_Latch_and_D_Flip_Flop/D_Flip_Flop/dFF_dLatch.v
// dff using 2 D-Latch
module dff (d, clk, q, qn);
	
	input d, clk;
	output q, qn;
	
	wire q0, qn0;
	wire clkn, clknn;
	
	not	inv1 (clkn, clk);
	not inv2 (clknn, clkn);
	
	d_latch d_master (d, clkn, q0, qn0);
	d_latch d_slave	 (q0, clknn, q, qn);

endmodule

Basic/5_Seqimtial_Circuit_Design/1_D_Latch_and_D_Flip_Flop/D_Flip_Flop/dff_tb.v
`timescale 1ns/1ns

module dff_tb;
	reg clk, d;
	wire q, qn;

	dff dff (d, clk, q, qn);

	initial begin
		#0 clk = 0;
		 	 d = 0;
		#2   d = 1;
		#2   d = 0;
		#2   d = 1;
		#2   d = 0;
		#1   d = 1;
		#2   d = 0;
		#3   d = 1;
		#2   d = 0;
		#2   d = 1;
		#1   d = 0;
		#2   d = 1;
		#3   d = 0;
		#6   $finish;
	end
	
	initial begin
		$dumpfile("dff.vcd");
		$dumpvars;
	
	end


	always #5 clk = !clk;

endmodule

basic/5_Seqimtial_Circuit_Design/1_D_Latch_and_D_Flip_Flop/D_Flip_Flop/dff.vcd
$date
	Wed Jan 31 21:07:41 2018
$end
$version
	Icarus Verilog
$end
$timescale
	1ns
$end
$scope module dff_tb $end
$var wire 1 ! qn $end
$var wire 1 " q $end
$var reg 1 # clk $end
$var reg 1 $ d $end
$scope module dff $end
$var wire 1 # clk $end
$var wire 1 % clkn $end
$var wire 1 & clknn $end
$var wire 1 $ d $end
$var wire 1 ' qn0 $end
$var wire 1 ! qn $end
$var wire 1 ( q0 $end
$var wire 1 " q $end
$scope module d_master $end
$var wire 1 % c $end
$var wire 1 $ d $end
$var wire 1 ) r $end
$var wire 1 * s $end
$var wire 1 ' qn $end
$var wire 1 ( q $end
$scope module rs $end
$var wire 1 ( q $end
$var wire 1 ' qn $end
$var wire 1 ) r $end
$var wire 1 * s $end
$upscope $end
$upscope $end
$scope module d_slave $end
$var wire 1 & c $end
$var wire 1 ( d $end
$var wire 1 + r $end
$var wire 1 , s $end
$var wire 1 ! qn $end
$var wire 1 " q $end
$scope module rs $end
$var wire 1 " q $end
$var wire 1 ! qn $end
$var wire 1 + r $end
$var wire 1 , s $end
$upscope $end
$upscope $end
$upscope $end
$upscope $end
$enddefinitions $end
#0
$dumpvars
1,
1+
1*
0)
0(
1'
0&
1%
0$
0#
x"
x!
$end
#2
0'
1(
1)
0*
1$
#4
0(
1'
0)
1*
0$
#5
0"
1!
0+
1&
1)
0%
1#
#6
1$
#8
0$
#9
1$
#10
0'
1+
1(
0&
0*
1%
0#
#11
0(
1'
0)
1*
0$
#14
0'
1(
1)
0*
1$
#15
0!
1"
0,
1&
1*
0%
1#
#16
0$
#18
1$
#19
0$
#20
0(
1,
1'
0&
0)
1%
0#
#21
0'
1(
1)
0*
1$
#24
0(
1'
0)
1*
0$
#25
0"
1!
0+
1&
1)
0%
1#
#30
1+
0&
0)
1%
0#
