Basic/5_Seqimtial_Circuit_Design/1_D_Latch_and_D_Flip_Flop/D_Flip_Flop/dFF_Schematic.v
// dff generated from schematic, industry way
module dff (prn, clk, d, clrn, q, qn);
	input prn, clk, d, clrn;						//prn: preset; cln: clear (active low);
	output q, qn;
	
	wire wire_0, wire_1, wire_2, wire_3;  

	assign wire_0 = ~(wire_1 & prn 	& wire_2); 	//3-input nand
	assign wire_1 = ~(clk 	 & clrn & wire_0);
	assign wire_2 = ~(wire_3 & clrn & d);
	assign wire_3 = ~(wire_1 & clk  & wire_2);
	
	assign q = ~(prn & wire_1 & qn);
	assign qn = ~(q & wire_3 & clrn);
	
endmodule

Basic/5_Seqimtial_Circuit_Design/1_D_Latch_and_D_Flip_Flop/D_Flip_Flop/dFF_Schematic_tb.v
`timescale 1ns/1ns

module dff_tb;
	reg prn, clk, d, clrn;
	wire q, qn;

	dff dff (prn, clk, d, clrn, q, qn);

	initial begin
		#0 clk 	= 0;
		   prn 	= 1;
		   clrn = 0;
		 	 d 	= 0;

		#1 clrn = 1;
		#1 prn 	= 0;
			d	= 1;
		#1 prn  = 1;
		#1 	d 	= 0;
		#2   d 	= 1;
		#2   d 	= 0;
		#1   d 	= 1;
		#2   d 	= 0;
		#3   d 	= 1;
		#2   d 	= 0;
		#2   d 	= 1;
		#1   d 	= 0;
		#2   d 	= 1;
		#3   d 	= 0;
		#6   $finish;
	end
	
	initial begin
		$dumpfile("dFF_Schematic.vcd");
		$dumpvars;
	
	end


	always #5 clk = !clk;

endmodule

Basic/5_Seqimtial_Circuit_Design/1_D_Latch_and_D_Flip_Flop/D_Flip_Flop/dFF_Schematic.vcd
$date
	Wed Jan 31 21:24:18 2018
$end
$version
	Icarus Verilog
$end
$timescale
	1ns
$end
$scope module dff_tb $end
$var wire 1 ! qn $end
$var wire 1 " q $end
$var reg 1 # clk $end
$var reg 1 $ clrn $end
$var reg 1 % d $end
$var reg 1 & prn $end
$scope module dff $end
$var wire 1 # clk $end
$var wire 1 $ clrn $end
$var wire 1 % d $end
$var wire 1 & prn $end
$var wire 1 " q $end
$var wire 1 ! qn $end
$var wire 1 ' wire_0 $end
$var wire 1 ( wire_1 $end
$var wire 1 ) wire_2 $end
$var wire 1 * wire_3 $end
$upscope $end
$upscope $end
$enddefinitions $end
#0
$dumpvars
1*
1)
1(
0'
1&
0%
0$
0#
0"
1!
$end
#1
1$
#2
0!
1'
1"
0)
1%
0&
#3
1&
#4
0'
1)
0%
#5
0"
1!
0*
1#
#6
1%
#8
0%
#9
1%
#10
1'
0)
1*
0#
#11
0'
1)
0%
#14
1'
0)
1%
#15
0!
1"
0(
1#
#16
1)
0%
#18
0)
1%
#19
1)
0%
#20
0'
1(
0#
#21
1'
0)
1%
#24
0'
1)
0%
#25
0"
1!
0*
1#
#30
1*
0#
