Basic/5_Seqimtial_Circuit_Design/2_JK_Latch_and_JK_Flip_Flop/jkff.v
// jk_latch is rarely used, because it toggles without speed control
// jk_ff is common used.
// jk_ff with asynchronous reset 
module jkff (j, k, clk, clrn, q);
	
	input j ,k, clk, clrn;
	output reg q;
	
	always @ (posedge clk or negedge clrn) begin
		if (!clrn)	q <= 0;
		else 		q <= j & ~q | ~k & q;
	end

	
endmodule

basic/5_Seqimtial_Circuit_Design/2_JK_Latch_and_JK_Flip_Flop/jkff_tb.v
`timescale 1ns/1ns
module jkff_tb;

	reg j, k, clk, clrn;
	wire q;

	jkff jkff(j, k, clk, clrn, q);

	initial begin
		 clk = 1; clrn = 0;
		 j = 0; k = 0;
		 #1 clrn = 1; k = 1;
		 #2 k = 0; j = 1;
		 #2 j = 0;
		 #2 k = 1; j = 1;
		 #8 k = 0; j = 0;
		 #2 $finish;
	end
	
	initial begin
		$dumpfile("jkff.vcd");
		$dumpvars;
	end

	always #1 clk = !clk;

endmodule

Basic/5_Seqimtial_Circuit_Design/2_JK_Latch_and_JK_Flip_Flop/jkff.vcd
$date
	Wed Jan 31 21:36:28 2018
$end
$version
	Icarus Verilog
$end
$timescale
	1ns
$end
$scope module jkff_tb $end
$var wire 1 ! q $end
$var reg 1 " clk $end
$var reg 1 # clrn $end
$var reg 1 $ j $end
$var reg 1 % k $end
$scope module jkff $end
$var wire 1 " clk $end
$var wire 1 # clrn $end
$var wire 1 $ j $end
$var wire 1 % k $end
$var reg 1 ! q $end
$upscope $end
$upscope $end
$enddefinitions $end
#0
$dumpvars
0%
0$
0#
1"
0!
$end
#1
0"
1%
1#
#2
1"
#3
0"
1$
0%
#4
1!
1"
#5
0"
0$
#6
1"
#7
0"
1$
1%
#8
0!
1"
#9
0"
#10
1!
1"
#11
0"
#12
0!
1"
#13
0"
#14
1!
1"
#15
0"
0$
0%
